drip/__init__.py
drip/cli.py
drip/drip_config.yaml
drip/flask_app/NAMES.DIC
drip/flask_app/README.rst
drip/flask_app/config.py
drip/flask_app/run.py
drip/flask_app/testdata.py
drip/flask_app/__pycache__/config.cpython-39.pyc
drip/flask_app/app/__init__.py
drip/flask_app/app/index.py
drip/flask_app/app/models.py
drip/flask_app/app/views.py
drip/flask_app/app/__pycache__/__init__.cpython-39.pyc
drip/flask_app/app/__pycache__/index.cpython-39.pyc
drip/flask_app/app/__pycache__/models.cpython-39.pyc
drip/flask_app/app/__pycache__/views.cpython-39.pyc
drip/flask_app/app/templates/index.html
drip/flask_app/app/translations/pt/LC_MESSAGES/messages.mo
drip/flask_app/app/translations/pt/LC_MESSAGES/messages.po
drip/flask_app/babel/babel.cfg
drip/flask_app/babel/messages.pot
drip/flask_app/babel/messages.pot~
drip/test/test_fichedata.py
drip/test/test_handlers.py
shihua_drip-0.1.dist-info/LICENSE
shihua_drip-0.1.dist-info/METADATA
shihua_drip-0.1.dist-info/WHEEL
shihua_drip-0.1.dist-info/entry_points.txt
shihua_drip-0.1.dist-info/top_level.txt
shihua_drip-0.1.dist-info/RECORD
